_pylcs.cp38-win_amd64.pyd
pylcs/__init__.py
pylcs-0.1.1.dist-info/LICENSE
pylcs-0.1.1.dist-info/METADATA
pylcs-0.1.1.dist-info/WHEEL
pylcs-0.1.1.dist-info/top_level.txt
pylcs-0.1.1.dist-info/RECORD
