Metadata-Version: 2.1
Name: pylcs
Version: 0.1.1
Summary: super fast cpp implementation of longest common subsequence
Home-page: https://github.com/kuangkzh/pylcs
Author: kuangzh
Author-email: kuangzh@smail.nju.edu.cn
License: Apache 2.0
Platform: UNKNOWN
Requires-Dist: pybind11 (>=2.2)
